MANIFEST.in
README.rst
setup.cfg
setup.py
django_admin_panel_arnika.egg-info/PKG-INFO
django_admin_panel_arnika.egg-info/SOURCES.txt
django_admin_panel_arnika.egg-info/dependency_links.txt
django_admin_panel_arnika.egg-info/requires.txt
django_admin_panel_arnika.egg-info/top_level.txt
jazzmin/__init__.py
jazzmin/apps.py
jazzmin/compat.py
jazzmin/forms.py
jazzmin/settings.py
jazzmin/utils.py
jazzmin/view.py
jazzmin/widgets.py
jazzmin/locale/bg/LC_MESSAGES/django.mo
jazzmin/locale/bg/LC_MESSAGES/django.po
jazzmin/locale/de/LC_MESSAGES/django.mo
jazzmin/locale/de/LC_MESSAGES/django.po
jazzmin/locale/es/LC_MESSAGES/django.mo
jazzmin/locale/es/LC_MESSAGES/django.po
jazzmin/locale/fa/LC_MESSAGES/django.mo
jazzmin/locale/fa/LC_MESSAGES/django.po
jazzmin/locale/hu/LC_MESSAGES/django.mo
jazzmin/locale/hu/LC_MESSAGES/django.po
jazzmin/locale/ru/LC_MESSAGES/django.mo
jazzmin/locale/ru/LC_MESSAGES/django.po
jazzmin/locale/zh_Hans/LC_MESSAGES/django.mo
jazzmin/locale/zh_Hans/LC_MESSAGES/django.po
jazzmin/locale/zh_Hant/LC_MESSAGES/django.mo
jazzmin/locale/zh_Hant/LC_MESSAGES/django.po
jazzmin/static/admin/js/cancel.js
jazzmin/static/admin/js/popup_response.js
jazzmin/static/jazzmin/css/main.css
jazzmin/static/jazzmin/css/rebot-rtl.css
jazzmin/static/jazzmin/css/style-login.css
jazzmin/static/jazzmin/css/template-rebot-rtl.css
jazzmin/static/jazzmin/fonts/CHANGELOG.md
jazzmin/static/jazzmin/fonts/LICENSE
jazzmin/static/jazzmin/fonts/README.md
jazzmin/static/jazzmin/fonts/Vazir-Bold.eot
jazzmin/static/jazzmin/fonts/Vazir-Bold.ttf
jazzmin/static/jazzmin/fonts/Vazir-Bold.woff
jazzmin/static/jazzmin/fonts/Vazir-Bold.woff2
jazzmin/static/jazzmin/fonts/Vazir-Light.eot
jazzmin/static/jazzmin/fonts/Vazir-Light.ttf
jazzmin/static/jazzmin/fonts/Vazir-Light.woff
jazzmin/static/jazzmin/fonts/Vazir-Light.woff2
jazzmin/static/jazzmin/fonts/Vazir-Medium.eot
jazzmin/static/jazzmin/fonts/Vazir-Medium.ttf
jazzmin/static/jazzmin/fonts/Vazir-Medium.woff
jazzmin/static/jazzmin/fonts/Vazir-Medium.woff2
jazzmin/static/jazzmin/fonts/Vazir-Thin.eot
jazzmin/static/jazzmin/fonts/Vazir-Thin.ttf
jazzmin/static/jazzmin/fonts/Vazir-Thin.woff
jazzmin/static/jazzmin/fonts/Vazir-Thin.woff2
jazzmin/static/jazzmin/fonts/Vazir.eot
